{"name":"Train 503","records":{"2018-01-01":{"cancelled":false,"missing_data":false,"delay":51,"actual_arrival":"1251","lines":[{"stop":"SEA","missing_data":false,"scheduled_arrival":"*","actual_arrival":"*","scheduled_departure":"840A","actual_departure":"922A"},{"stop":"TUK","missing_data":true},{"stop":"TAC","missing_data":false,"scheduled_arrival":"*","actual_arrival":"*","scheduled_departure":"925A","actual_departure":"1011"},{"stop":"OLW","missing_data":false,"scheduled_arrival":"*","actual_arrival":"*","scheduled_departure":"955A","actual_departure":"1051"},{"stop":"CTL","missing_data":false,"scheduled_arrival":"*","actual_arrival":"*","scheduled_departure":"1015A","actual_departure":"1112"},{"stop":"KEL","missing_data":true},{"stop":"VAN","missing_data":false,"scheduled_arrival":"*","actual_arrival":"*","scheduled_departure":"1131A","actual_departure":"1233"},{"stop":"PDX","missing_data":false,"scheduled_arrival":"1200P","actual_arrival":"1251","scheduled_departure":"*","actual_departure":"*"}],"raw":"* Amtrak Cascades\r\n* +---------------- Station Code\r\n* |    +----------- Schedule Arrival Day  \r\n* |    |  +-------- Schedule Arrival Time\r\n* |    |  |     +----- Schedule Departure Day\r\n* |    |  |     |  +-- Schedule Departure Time \r\n* |    |  |     |  |     +------------- Actual Arrival Time\r\n* |    |  |     |  |     |     +------- Actual Departure Time\r\n* |    |  |     |  |     |     |     +- Comments\r\n* V    V  V     V  V     V     V     V\r\n* SEA  *  *     1  840A  *     922A  Departed:  42 minutes late.\r\n  TUK  *  *     1  854A              PT\r\n* TAC  *  *     1  925A  *     1011A Departed:  46 minutes late.\r\n* OLW  *  *     1  955A  *     1051A Departed:  56 minutes late.\r\n* CTL  *  *     1  1015A *     1112A Departed:  57 minutes late.\r\n  KEL  *  *     1  1055A             PT\r\n* VAN  *  *     1  1131A *     1233P Departed:  1 hour, 2 minutes late.\r\n* PDX  1  1200P *  *     1251P *     Arrived:  51 minutes late.\r\n"}},"origin":{"stop":"SEA","time":"840A"},"destination":{"stop":"PDX","time":"1200P"},"route":"Amtrak Cascades","stats":{"cancellations":0,"missing_data":0,"valid_records":1,"median":51,"p90":51}}